rfcxtf/ClassifierBase.py
rfcxtf/ClassifierTF2.py
rfcxtf/__init__.py
rfcxtf/validate.py
rfcxtf/utils/__init__.py
rfcxtf/utils/exceptions.py
rfcxtf/utils/io.py
rfcxtf/utils/postprocessor.py
rfcxtf-0.0.5.dist-info/METADATA
rfcxtf-0.0.5.dist-info/WHEEL
rfcxtf-0.0.5.dist-info/top_level.txt
rfcxtf-0.0.5.dist-info/RECORD
